leonardorpires/__init__.py
leonardorpires/config/config.ini
leonardorpires/infrastructure/__init__.py
leonardorpires/infrastructure/azure/__init__.py
leonardorpires/infrastructure/azure/authentication/__init__.py
leonardorpires/infrastructure/azure/authentication/api.py
leonardorpires/infrastructure/azure/authentication/key_vault.py
leonardorpires/infrastructure/azure/key_vault/__init__.py
leonardorpires/infrastructure/azure/key_vault/key_vault.py
leonardorpires/infrastructure/azure/purview/__init__.py
leonardorpires/infrastructure/azure/purview/purview.py
leonardorpires/infrastructure/azure/purview/purview_mapper.py
leonardorpires/infrastructure/common/__init__.py
leonardorpires/infrastructure/common/config.py
leonardorpires/infrastructure/common/either.py
leonardorpires/infrastructure/common/exception.py
leonardorpires/infrastructure/common/feature_flag.py
leonardorpires/infrastructure/common/helper.py
leonardorpires/infrastructure/common/message.py
leonardorpires/infrastructure/common/message_mapper.py
leonardorpires/infrastructure/integration/__init__.py
leonardorpires/infrastructure/integration/database/__init__.py
leonardorpires/infrastructure/integration/database/connection_factory.py
leonardorpires/infrastructure/integration/database/repository_integration.py
leonardorpires/infrastructure/integration/datadog/__init__.py
leonardorpires/infrastructure/integration/datadog/datadog.py
leonardorpires/infrastructure/integration/git/__init__.py
leonardorpires/infrastructure/integration/git/git.py
leonardorpires/infrastructure/integration/mlflow/__init__.py
leonardorpires/infrastructure/integration/mlflow/mlflow.py
leonardorpires/infrastructure/integration/ms_teams/__init__.py
leonardorpires/infrastructure/integration/ms_teams/ms_teams.py
leonardorpires/infrastructure/integration/servicebus/__init__.py
leonardorpires/infrastructure/integration/servicebus/servicebus_connection.py
leonardorpires/infrastructure/metadata/__init__.py
leonardorpires-2.5.1.dist-info/WHEEL
leonardorpires-2.5.1.dist-info/METADATA
leonardorpires-2.5.1.dist-info/RECORD
