Metadata-Version: 2.1
Name: leonardorpires
Version: 2.5.1
Summary: This library provides tools for building Extract, Transform, and Load modules using Apache Spark and Pandas. It is a central framework to help create Data Pipeline and Machine Learning Models. 
Home-page: https://github.com/cervejaria-ambev/pyiris
Author: Iris - Data Platform Team
Requires-Python: >=3.8.0,<3.9.0
Classifier: Programming Language :: Python :: 3
Classifier: Programming Language :: Python :: 3.8
Requires-Dist: Office365-REST-Python-Client (==2.3.9)
Requires-Dist: SQLAlchemy (==1.4.9)
Requires-Dist: azure-identity (==1.5.0)
Requires-Dist: azure-keyvault-secrets (==4.2.0)
Requires-Dist: azure-servicebus (==7.8.0)
Requires-Dist: cerberus (==1.3.2)
Requires-Dist: datadog (==0.44.0)
Requires-Dist: loguru (==0.6.0)
Requires-Dist: mlflow (==1.25.1)
Requires-Dist: pandas (==1.3.5)
Requires-Dist: pika (==1.2.0)
Requires-Dist: protobuf (==3.20.0)
Requires-Dist: psycopg2-binary (==2.8.6)
Requires-Dist: pymsteams (==0.2.1)
Requires-Dist: python-semantic-release (==7.31.4)
Requires-Dist: pyyaml (==5.4.1)
Requires-Dist: smbprotocol (==1.8.3)
Requires-Dist: sphinx (==5.0.0)
Requires-Dist: sqlalchemy-utils (==0.38.2)
Requires-Dist: toml (==0.10.0)
Requires-Dist: trino (==0.305.0)
Project-URL: Repository, https://github.com/cervejaria-ambev/pyiris
